medlab/__init__.py
medlab/requirements.txt
medlab/configs/_base_/models/classification/alexnet/alexnet_torchvision.py
medlab/configs/_base_/models/classification/convnext/convnext_base_torchvision.py
medlab/configs/_base_/models/classification/convnext/convnext_large_torchvision.py
medlab/configs/_base_/models/classification/convnext/convnext_small_torchvision.py
medlab/configs/_base_/models/classification/convnext/convnext_tiny_torchvision.py
medlab/configs/_base_/models/classification/densenet/densenet121_torchvision.py
medlab/configs/_base_/models/classification/densenet/densenet161_torchvision.py
medlab/configs/_base_/models/classification/densenet/densenet169_torchvision.py
medlab/configs/_base_/models/classification/densenet/densenet201_torchvision.py
medlab/configs/_base_/models/classification/efficientnet/efficientnet_b0_torchvision.py
medlab/configs/_base_/models/classification/efficientnet/efficientnet_b1_torchvision.py
medlab/configs/_base_/models/classification/efficientnet/efficientnet_b2_torchvision.py
medlab/configs/_base_/models/classification/efficientnet/efficientnet_b3_torchvision.py
medlab/configs/_base_/models/classification/efficientnet/efficientnet_b4_torchvision.py
medlab/configs/_base_/models/classification/efficientnet/efficientnet_b5_torchvision.py
medlab/configs/_base_/models/classification/efficientnet/efficientnet_b6_torchvision.py
medlab/configs/_base_/models/classification/efficientnet/efficientnet_b7_torchvision.py
medlab/configs/_base_/models/classification/efficientnet/efficientnet_v2_l_torchvision.py
medlab/configs/_base_/models/classification/efficientnet/efficientnet_v2_m_torchvision.py
medlab/configs/_base_/models/classification/efficientnet/efficientnet_v2_s_torchvision.py
medlab/configs/_base_/models/classification/inception/inception_v3_torchvision.py
medlab/configs/_base_/models/classification/maxvit/maxvit_t_torchvision.py
medlab/configs/_base_/models/classification/mobilenet/mobilenet_v2_torchvision.py
medlab-2024.2.3.dist-info/LICENSE
medlab-2024.2.3.dist-info/METADATA
medlab-2024.2.3.dist-info/WHEEL
medlab-2024.2.3.dist-info/entry_points.txt
medlab-2024.2.3.dist-info/top_level.txt
medlab-2024.2.3.dist-info/RECORD
