Metadata-Version: 2.1
Name: medlab
Version: 2024.2.3
Summary: medical deep learning toolkit
Home-page: https://gitee.com/Eason596/py-package-release-test
Author: yjiang
Author-email: 1900812907@qq.com
License: MIT
Requires-Python: >=3.8
License-File: LICENSE
